setup.py
docs/HISTORY.txt
docs/README.txt
teamrubber/__init__.py
teamrubber.theoracle.egg-info/PKG-INFO
teamrubber.theoracle.egg-info/SOURCES.txt
teamrubber.theoracle.egg-info/dependency_links.txt
teamrubber.theoracle.egg-info/entry_points.txt
teamrubber.theoracle.egg-info/namespace_packages.txt
teamrubber.theoracle.egg-info/not-zip-safe
teamrubber.theoracle.egg-info/requires.txt
teamrubber.theoracle.egg-info/top_level.txt
teamrubber/theoracle/__init__.py
teamrubber/theoracle/configure.zcml
teamrubber/theoracle/debugger.py
teamrubber/theoracle/interfaces.py
teamrubber/theoracle/utils.py
teamrubber/theoracle/browser/__init__.py
teamrubber/theoracle/browser/attributes.py
teamrubber/theoracle/browser/breaks.py
teamrubber/theoracle/browser/callables.py
teamrubber/theoracle/browser/catalog.py
teamrubber/theoracle/browser/configure.zcml
teamrubber/theoracle/browser/context.py
teamrubber/theoracle/browser/opdb.py
teamrubber/theoracle/browser/request.py
teamrubber/theoracle/browser/root.py
teamrubber/theoracle/browser/source.py
teamrubber/theoracle/browser/user.py
teamrubber/theoracle/browser/views.py
teamrubber/theoracle/browser/resources/style.css
teamrubber/theoracle/browser/templates/attributes.pt
teamrubber/theoracle/browser/templates/breaks.pt
teamrubber/theoracle/browser/templates/callables.pt
teamrubber/theoracle/browser/templates/catalog.pt
teamrubber/theoracle/browser/templates/context.pt
teamrubber/theoracle/browser/templates/request.pt
teamrubber/theoracle/browser/templates/source.pt
teamrubber/theoracle/browser/templates/source_full.pt
teamrubber/theoracle/browser/templates/the_oracle.pt
teamrubber/theoracle/browser/templates/user.pt
teamrubber/theoracle/browser/templates/views.pt