Metadata-Version: 1.0
Name: teamrubber.theoracle
Version: 1.0
Summary: Plone debug/development helper
Home-page: http://www.teamrubber.com
Author: Alan Hoey
Author-email: alan.hoey@teamrubber.com
License: GPL
Platform: UNKNOWN
Classifier: Framework :: Plone
Classifier: Programming Language :: Python
Classifier: Topic :: Software Development :: Libraries :: Python Modules
